<?xml version="1.0"?>
    <BinaryTree type="DecisionTree" boostWeight="1.0000000000000000e+00" itree="8">
      <Node pos="s" depth="0" NCoef="0" IVar="11" Cut="5.2400000000000000e+02" cType="1" res="-1.7383765429258347e-02" rms="-nan" purity="0.0000000000000000e+00" nType="0">
        <Node pos="l" depth="1" NCoef="0" IVar="11" Cut="2.5500000000000000e+02" cType="1" res="0.0000000000000000e+00" rms="0.0000000000000000e+00" purity="0.0000000000000000e+00" nType="0">
          <Node pos="l" depth="2" NCoef="0" IVar="4" Cut="-5.0000000000000000e+00" cType="1" res="2.1603457629680634e-02" rms="5.1319807767868042e-01" purity="0.0000000000000000e+00" nType="0">
            <Node pos="l" depth="3" NCoef="0" IVar="3" Cut="-2.0000000000000000e+00" cType="1" res="2.4245036765933037e-02" rms="3.9985346794128418e-01" purity="0.0000000000000000e+00" nType="0">
              <Node pos="l" depth="4" NCoef="0" IVar="0" Cut="1.0000000000000000e+00" cType="1" res="-1.6352064907550812e-02" rms="5.6360658258199692e-02" purity="0.0000000000000000e+00" nType="0">
                <Node pos="l" depth="5" NCoef="0" IVar="-1" Cut="0.0000000000000000e+00" cType="1" res="3.0699567869305611e-03" rms="8.9847818017005920e-02" purity="0.0000000000000000e+00" nType="-99"/>
                <Node pos="r" depth="5" NCoef="0" IVar="-1" Cut="0.0000000000000000e+00" cType="1" res="-2.2326379548758268e-03" rms="4.7308076173067093e-02" purity="0.0000000000000000e+00" nType="-99"/>
              </Node>
              <Node pos="r" depth="4" NCoef="0" IVar="2" Cut="3.9000000000000000e+01" cType="1" res="0.0000000000000000e+00" rms="0.0000000000000000e+00" purity="0.0000000000000000e+00" nType="0">
                <Node pos="l" depth="5" NCoef="0" IVar="-1" Cut="0.0000000000000000e+00" cType="1" res="-7.1460474282503128e-03" rms="5.0530016422271729e-02" purity="0.0000000000000000e+00" nType="-99"/>
                <Node pos="r" depth="5" NCoef="0" IVar="-1" Cut="0.0000000000000000e+00" cType="1" res="-3.4395190887153149e-03" rms="5.5488772690296173e-02" purity="0.0000000000000000e+00" nType="-99"/>
              </Node>
            </Node>
            <Node pos="r" depth="3" NCoef="0" IVar="2" Cut="3.5000000000000000e+01" cType="1" res="0.0000000000000000e+00" rms="0.0000000000000000e+00" purity="0.0000000000000000e+00" nType="0">
              <Node pos="l" depth="4" NCoef="0" IVar="0" Cut="8.0000000000000000e+00" cType="1" res="-8.3142757415771484e-02" rms="2.7305191382765770e-02" purity="0.0000000000000000e+00" nType="0">
                <Node pos="l" depth="5" NCoef="0" IVar="-1" Cut="0.0000000000000000e+00" cType="1" res="-8.7780738249421120e-03" rms="2.6933608576655388e-02" purity="0.0000000000000000e+00" nType="-99"/>
                <Node pos="r" depth="5" NCoef="0" IVar="-1" Cut="0.0000000000000000e+00" cType="1" res="-7.4843396432697773e-03" rms="2.5966642424464226e-02" purity="0.0000000000000000e+00" nType="-99"/>
              </Node>
              <Node pos="r" depth="4" NCoef="0" IVar="1" Cut="1.0000000000000000e+00" cType="1" res="-1.7703749239444733e-02" rms="3.5869404673576355e-02" purity="0.0000000000000000e+00" nType="0">
                <Node pos="l" depth="5" NCoef="0" IVar="-1" Cut="0.0000000000000000e+00" cType="1" res="-6.6570420749485493e-03" rms="3.8462854921817780e-02" purity="0.0000000000000000e+00" nType="-99"/>
                <Node pos="r" depth="5" NCoef="0" IVar="-1" Cut="0.0000000000000000e+00" cType="1" res="-4.3161348439753056e-03" rms="3.4953828901052475e-02" purity="0.0000000000000000e+00" nType="-99"/>
              </Node>
            </Node>
          </Node>
          <Node pos="r" depth="2" NCoef="0" IVar="4" Cut="-5.0000000000000000e+00" cType="1" res="0.0000000000000000e+00" rms="0.0000000000000000e+00" purity="0.0000000000000000e+00" nType="0">
            <Node pos="l" depth="3" NCoef="0" IVar="0" Cut="2.0000000000000000e+00" cType="1" res="1.5334238298237324e-02" rms="6.8697728216648102e-02" purity="0.0000000000000000e+00" nType="0">
              <Node pos="l" depth="4" NCoef="0" IVar="7" Cut="-6.0000000000000000e+01" cType="1" res="0.0000000000000000e+00" rms="-nan" purity="0.0000000000000000e+00" nType="0">
                <Node pos="l" depth="5" NCoef="0" IVar="-1" Cut="0.0000000000000000e+00" cType="1" res="9.3813659623265266e-03" rms="9.8975829780101776e-02" purity="0.0000000000000000e+00" nType="-99"/>
                <Node pos="r" depth="5" NCoef="0" IVar="-1" Cut="0.0000000000000000e+00" cType="1" res="3.5572899505496025e-03" rms="7.9215526580810547e-02" purity="0.0000000000000000e+00" nType="-99"/>
              </Node>
              <Node pos="r" depth="4" NCoef="0" IVar="9" Cut="3.0000000000000000e+00" cType="1" res="-5.6880405172705650e-03" rms="3.9888996630907059e-02" purity="0.0000000000000000e+00" nType="0">
                <Node pos="l" depth="5" NCoef="0" IVar="-1" Cut="0.0000000000000000e+00" cType="1" res="-8.0314383376389742e-04" rms="5.2265349775552750e-02" purity="0.0000000000000000e+00" nType="-99"/>
                <Node pos="r" depth="5" NCoef="0" IVar="-1" Cut="0.0000000000000000e+00" cType="1" res="3.4000603482127190e-03" rms="3.9965741336345673e-02" purity="0.0000000000000000e+00" nType="-99"/>
              </Node>
            </Node>
            <Node pos="r" depth="3" NCoef="0" IVar="0" Cut="2.0000000000000000e+00" cType="1" res="-3.5046018660068512e-02" rms="5.3077794611454010e-02" purity="0.0000000000000000e+00" nType="0">
              <Node pos="l" depth="4" NCoef="0" IVar="4" Cut="4.0000000000000000e+00" cType="1" res="0.0000000000000000e+00" rms="0.0000000000000000e+00" purity="0.0000000000000000e+00" nType="0">
                <Node pos="l" depth="5" NCoef="0" IVar="-1" Cut="0.0000000000000000e+00" cType="1" res="-1.2231856817379594e-04" rms="6.1051741242408752e-02" purity="0.0000000000000000e+00" nType="-99"/>
                <Node pos="r" depth="5" NCoef="0" IVar="-1" Cut="0.0000000000000000e+00" cType="1" res="-2.9526392463594675e-03" rms="6.1395596712827682e-02" purity="0.0000000000000000e+00" nType="-99"/>
              </Node>
              <Node pos="r" depth="4" NCoef="0" IVar="0" Cut="8.0000000000000000e+00" cType="1" res="-4.6173591166734695e-02" rms="4.0872283279895782e-02" purity="0.0000000000000000e+00" nType="0">
                <Node pos="l" depth="5" NCoef="0" IVar="-1" Cut="0.0000000000000000e+00" cType="1" res="-5.5250711739063263e-03" rms="3.4629449248313904e-02" purity="0.0000000000000000e+00" nType="-99"/>
                <Node pos="r" depth="5" NCoef="0" IVar="-1" Cut="0.0000000000000000e+00" cType="1" res="-1.2198763433843851e-03" rms="4.4407885521650314e-02" purity="0.0000000000000000e+00" nType="-99"/>
              </Node>
            </Node>
          </Node>
        </Node>
        <Node pos="r" depth="1" NCoef="0" IVar="2" Cut="2.7700000000000000e+02" cType="1" res="0.0000000000000000e+00" rms="0.0000000000000000e+00" purity="0.0000000000000000e+00" nType="0">
          <Node pos="l" depth="2" NCoef="0" IVar="4" Cut="-6.7000000000000000e+01" cType="1" res="0.0000000000000000e+00" rms="0.0000000000000000e+00" purity="0.0000000000000000e+00" nType="0">
            <Node pos="l" depth="3" NCoef="0" IVar="0" Cut="3.0000000000000000e+00" cType="1" res="9.1261126101016998e-02" rms="8.2821279764175415e-02" purity="0.0000000000000000e+00" nType="0">
              <Node pos="l" depth="4" NCoef="0" IVar="0" Cut="1.0000000000000000e+00" cType="1" res="1.3135133683681488e-01" rms="8.6503453552722931e-02" purity="0.0000000000000000e+00" nType="0">
                <Node pos="l" depth="5" NCoef="0" IVar="-1" Cut="0.0000000000000000e+00" cType="1" res="1.7772646620869637e-02" rms="9.5810353755950928e-02" purity="0.0000000000000000e+00" nType="-99"/>
                <Node pos="r" depth="5" NCoef="0" IVar="-1" Cut="0.0000000000000000e+00" cType="1" res="1.1571590788662434e-02" rms="7.7079281210899353e-02" purity="0.0000000000000000e+00" nType="-99"/>
              </Node>
              <Node pos="r" depth="4" NCoef="0" IVar="0" Cut="4.0000000000000000e+00" cType="1" res="5.1106996834278107e-02" rms="5.4888490587472916e-02" purity="0.0000000000000000e+00" nType="0">
                <Node pos="l" depth="5" NCoef="0" IVar="-1" Cut="0.0000000000000000e+00" cType="1" res="7.9360064119100571e-03" rms="5.4918974637985229e-02" purity="0.0000000000000000e+00" nType="-99"/>
                <Node pos="r" depth="5" NCoef="0" IVar="-1" Cut="0.0000000000000000e+00" cType="1" res="3.7579638883471489e-03" rms="4.9456700682640076e-02" purity="0.0000000000000000e+00" nType="-99"/>
              </Node>
            </Node>
            <Node pos="r" depth="3" NCoef="0" IVar="0" Cut="1.0000000000000000e+00" cType="1" res="2.7463572099804878e-02" rms="7.2049811482429504e-02" purity="0.0000000000000000e+00" nType="0">
              <Node pos="l" depth="4" NCoef="0" IVar="4" Cut="3.0000000000000000e+00" cType="1" res="0.0000000000000000e+00" rms="0.0000000000000000e+00" purity="0.0000000000000000e+00" nType="0">
                <Node pos="l" depth="5" NCoef="0" IVar="-1" Cut="0.0000000000000000e+00" cType="1" res="1.0664391331374645e-02" rms="8.7799355387687683e-02" purity="0.0000000000000000e+00" nType="-99"/>
                <Node pos="r" depth="5" NCoef="0" IVar="-1" Cut="0.0000000000000000e+00" cType="1" res="4.4708233326673508e-03" rms="8.8960207998752594e-02" purity="0.0000000000000000e+00" nType="-99"/>
              </Node>
              <Node pos="r" depth="4" NCoef="0" IVar="4" Cut="-5.0000000000000000e+00" cType="1" res="0.0000000000000000e+00" rms="0.0000000000000000e+00" purity="0.0000000000000000e+00" nType="0">
                <Node pos="l" depth="5" NCoef="0" IVar="-1" Cut="0.0000000000000000e+00" cType="1" res="3.4604838583618402e-03" rms="5.8844383805990219e-02" purity="0.0000000000000000e+00" nType="-99"/>
                <Node pos="r" depth="5" NCoef="0" IVar="-1" Cut="0.0000000000000000e+00" cType="1" res="6.5760614234022796e-05" rms="5.7390686124563217e-02" purity="0.0000000000000000e+00" nType="-99"/>
              </Node>
            </Node>
          </Node>
          <Node pos="r" depth="2" NCoef="0" IVar="0" Cut="2.0000000000000000e+00" cType="1" res="9.3141920864582062e-02" rms="7.5379811227321625e-02" purity="0.0000000000000000e+00" nType="0">
            <Node pos="l" depth="3" NCoef="0" IVar="2" Cut="3.6200000000000000e+02" cType="1" res="0.0000000000000000e+00" rms="0.0000000000000000e+00" purity="0.0000000000000000e+00" nType="0">
              <Node pos="l" depth="4" NCoef="0" IVar="15" Cut="3.0000000000000000e+00" cType="1" res="0.0000000000000000e+00" rms="0.0000000000000000e+00" purity="0.0000000000000000e+00" nType="0">
                <Node pos="l" depth="5" NCoef="0" IVar="-1" Cut="0.0000000000000000e+00" cType="1" res="1.0991312563419342e-02" rms="7.7388577163219452e-02" purity="0.0000000000000000e+00" nType="-99"/>
                <Node pos="r" depth="5" NCoef="0" IVar="-1" Cut="0.0000000000000000e+00" cType="1" res="1.8936032429337502e-02" rms="1.0038382560014725e-01" purity="0.0000000000000000e+00" nType="-99"/>
              </Node>
              <Node pos="r" depth="4" NCoef="0" IVar="15" Cut="3.0000000000000000e+00" cType="1" res="0.0000000000000000e+00" rms="0.0000000000000000e+00" purity="0.0000000000000000e+00" nType="0">
                <Node pos="l" depth="5" NCoef="0" IVar="-1" Cut="0.0000000000000000e+00" cType="1" res="1.5205129049718380e-02" rms="7.6972000300884247e-02" purity="0.0000000000000000e+00" nType="-99"/>
                <Node pos="r" depth="5" NCoef="0" IVar="-1" Cut="0.0000000000000000e+00" cType="1" res="2.3996783420443535e-02" rms="9.1803081333637238e-02" purity="0.0000000000000000e+00" nType="-99"/>
              </Node>
            </Node>
            <Node pos="r" depth="3" NCoef="0" IVar="0" Cut="4.0000000000000000e+00" cType="1" res="6.8448387086391449e-02" rms="5.7275578379631042e-02" purity="0.0000000000000000e+00" nType="0">
              <Node pos="l" depth="4" NCoef="0" IVar="2" Cut="3.9200000000000000e+02" cType="1" res="0.0000000000000000e+00" rms="0.0000000000000000e+00" purity="0.0000000000000000e+00" nType="0">
                <Node pos="l" depth="5" NCoef="0" IVar="-1" Cut="0.0000000000000000e+00" cType="1" res="7.3594553396105766e-03" rms="5.5019374936819077e-02" purity="0.0000000000000000e+00" nType="-99"/>
                <Node pos="r" depth="5" NCoef="0" IVar="-1" Cut="0.0000000000000000e+00" cType="1" res="1.1673328466713428e-02" rms="5.6982725858688354e-02" purity="0.0000000000000000e+00" nType="-99"/>
              </Node>
              <Node pos="r" depth="4" NCoef="0" IVar="4" Cut="-6.7000000000000000e+01" cType="1" res="0.0000000000000000e+00" rms="0.0000000000000000e+00" purity="0.0000000000000000e+00" nType="0">
                <Node pos="l" depth="5" NCoef="0" IVar="-1" Cut="0.0000000000000000e+00" cType="1" res="6.3292672857642174e-03" rms="4.4703662395477295e-02" purity="0.0000000000000000e+00" nType="-99"/>
                <Node pos="r" depth="5" NCoef="0" IVar="-1" Cut="0.0000000000000000e+00" cType="1" res="3.1823909375816584e-03" rms="4.2234551161527634e-02" purity="0.0000000000000000e+00" nType="-99"/>
              </Node>
            </Node>
          </Node>
        </Node>
      </Node>
    </BinaryTree>
