<?xml version="1.0"?>
    <BinaryTree type="DecisionTree" boostWeight="1.0000000000000000e+00" itree="240">
      <Node pos="s" depth="0" NCoef="0" IVar="4" Cut="4.7200000000000000e+02" cType="1" res="6.3894152641296387e-01" rms="5.4820728302001953e-01" purity="0.0000000000000000e+00" nType="0">
        <Node pos="l" depth="1" NCoef="0" IVar="4" Cut="4.6700000000000000e+02" cType="1" res="0.0000000000000000e+00" rms="0.0000000000000000e+00" purity="0.0000000000000000e+00" nType="0">
          <Node pos="l" depth="2" NCoef="0" IVar="4" Cut="4.5000000000000000e+02" cType="1" res="0.0000000000000000e+00" rms="0.0000000000000000e+00" purity="0.0000000000000000e+00" nType="0">
            <Node pos="l" depth="3" NCoef="0" IVar="4" Cut="4.4400000000000000e+02" cType="1" res="1.1078352481126785e-01" rms="4.9410057067871094e-01" purity="0.0000000000000000e+00" nType="0">
              <Node pos="l" depth="4" NCoef="0" IVar="4" Cut="4.4300000000000000e+02" cType="1" res="-1.3590235425908759e-07" rms="-nan" purity="0.0000000000000000e+00" nType="0">
                <Node pos="l" depth="5" NCoef="0" IVar="-1" Cut="0.0000000000000000e+00" cType="1" res="-7.8381827961493400e-07" rms="5.0901632755994797e-02" purity="0.0000000000000000e+00" nType="-99"/>
                <Node pos="r" depth="5" NCoef="0" IVar="-1" Cut="0.0000000000000000e+00" cType="1" res="-9.0275402180850506e-04" rms="4.7876805067062378e-02" purity="0.0000000000000000e+00" nType="-99"/>
              </Node>
              <Node pos="r" depth="4" NCoef="0" IVar="8" Cut="5.0000000000000000e+00" cType="1" res="4.5379428192973137e-03" rms="6.4757488667964935e-02" purity="0.0000000000000000e+00" nType="0">
                <Node pos="l" depth="5" NCoef="0" IVar="-1" Cut="0.0000000000000000e+00" cType="1" res="-3.8829894037917256e-05" rms="6.0179349035024643e-02" purity="0.0000000000000000e+00" nType="-99"/>
                <Node pos="r" depth="5" NCoef="0" IVar="-1" Cut="0.0000000000000000e+00" cType="1" res="2.9232080560177565e-03" rms="8.2159824669361115e-02" purity="0.0000000000000000e+00" nType="-99"/>
              </Node>
            </Node>
            <Node pos="r" depth="3" NCoef="0" IVar="0" Cut="3.0000000000000000e+00" cType="1" res="-1.9638349767774343e-03" rms="6.2339883297681808e-02" purity="0.0000000000000000e+00" nType="0">
              <Node pos="l" depth="4" NCoef="0" IVar="7" Cut="3.0000000000000000e+00" cType="1" res="0.0000000000000000e+00" rms="0.0000000000000000e+00" purity="0.0000000000000000e+00" nType="0">
                <Node pos="l" depth="5" NCoef="0" IVar="-1" Cut="0.0000000000000000e+00" cType="1" res="-1.0704252636060119e-03" rms="7.5096249580383301e-02" purity="0.0000000000000000e+00" nType="-99"/>
                <Node pos="r" depth="5" NCoef="0" IVar="-1" Cut="0.0000000000000000e+00" cType="1" res="4.6597243635915220e-04" rms="8.1980593502521515e-02" purity="0.0000000000000000e+00" nType="-99"/>
              </Node>
              <Node pos="r" depth="4" NCoef="0" IVar="7" Cut="2.0000000000000000e+00" cType="1" res="1.1979946866631508e-03" rms="5.0868388265371323e-02" purity="0.0000000000000000e+00" nType="0">
                <Node pos="l" depth="5" NCoef="0" IVar="-1" Cut="0.0000000000000000e+00" cType="1" res="-2.2224031854420900e-03" rms="5.2403707057237625e-02" purity="0.0000000000000000e+00" nType="-99"/>
                <Node pos="r" depth="5" NCoef="0" IVar="-1" Cut="0.0000000000000000e+00" cType="1" res="1.8947596254292876e-04" rms="5.2337292581796646e-02" purity="0.0000000000000000e+00" nType="-99"/>
              </Node>
            </Node>
          </Node>
          <Node pos="r" depth="2" NCoef="0" IVar="6" Cut="1.0000000000000000e+00" cType="1" res="-1.8092977115884423e-03" rms="1.8791537731885910e-02" purity="0.0000000000000000e+00" nType="0">
            <Node pos="l" depth="3" NCoef="0" IVar="8" Cut="2.0000000000000000e+00" cType="1" res="-2.3585854098200798e-02" rms="3.1430918723344803e-02" purity="0.0000000000000000e+00" nType="0">
              <Node pos="l" depth="4" NCoef="0" IVar="3" Cut="-1.0000000000000000e+00" cType="1" res="-1.1594882234930992e-03" rms="6.6040335223078728e-03" purity="0.0000000000000000e+00" nType="0">
                <Node pos="l" depth="5" NCoef="0" IVar="-1" Cut="0.0000000000000000e+00" cType="1" res="-1.9282030407339334e-03" rms="8.3188982680439949e-03" purity="0.0000000000000000e+00" nType="-99"/>
                <Node pos="r" depth="5" NCoef="0" IVar="-1" Cut="0.0000000000000000e+00" cType="1" res="-3.1902259797789156e-04" rms="2.0344529300928116e-02" purity="0.0000000000000000e+00" nType="-99"/>
              </Node>
              <Node pos="r" depth="4" NCoef="0" IVar="0" Cut="4.0000000000000000e+00" cType="1" res="-4.1464947164058685e-02" rms="3.6627314984798431e-02" purity="0.0000000000000000e+00" nType="0">
                <Node pos="l" depth="5" NCoef="0" IVar="-1" Cut="0.0000000000000000e+00" cType="1" res="-1.0196175426244736e-02" rms="1.8752751871943474e-02" purity="0.0000000000000000e+00" nType="-99"/>
                <Node pos="r" depth="5" NCoef="0" IVar="-1" Cut="0.0000000000000000e+00" cType="1" res="-2.9125553555786610e-03" rms="2.5391180068254471e-02" purity="0.0000000000000000e+00" nType="-99"/>
              </Node>
            </Node>
            <Node pos="r" depth="3" NCoef="0" IVar="8" Cut="4.0000000000000000e+00" cType="1" res="-3.8366981316357851e-03" rms="4.1334122419357300e-02" purity="0.0000000000000000e+00" nType="0">
              <Node pos="l" depth="4" NCoef="0" IVar="0" Cut="3.0000000000000000e+00" cType="1" res="-9.3703903257846832e-03" rms="4.0490619838237762e-02" purity="0.0000000000000000e+00" nType="0">
                <Node pos="l" depth="5" NCoef="0" IVar="-1" Cut="0.0000000000000000e+00" cType="1" res="3.1313146464526653e-03" rms="0.0000000000000000e+00" purity="0.0000000000000000e+00" nType="-99"/>
                <Node pos="r" depth="5" NCoef="0" IVar="-1" Cut="0.0000000000000000e+00" cType="1" res="-1.2634643353521824e-03" rms="4.0343258529901505e-02" purity="0.0000000000000000e+00" nType="-99"/>
              </Node>
              <Node pos="r" depth="4" NCoef="0" IVar="5" Cut="1.0000000000000000e+00" cType="1" res="4.0027081966400146e-02" rms="1.7674945294857025e-02" purity="0.0000000000000000e+00" nType="0">
                <Node pos="l" depth="5" NCoef="0" IVar="-1" Cut="0.0000000000000000e+00" cType="1" res="5.5932966060936451e-03" rms="0.0000000000000000e+00" purity="0.0000000000000000e+00" nType="-99"/>
                <Node pos="r" depth="5" NCoef="0" IVar="-1" Cut="0.0000000000000000e+00" cType="1" res="2.6461330708116293e-03" rms="1.8354192376136780e-02" purity="0.0000000000000000e+00" nType="-99"/>
              </Node>
            </Node>
          </Node>
        </Node>
        <Node pos="r" depth="1" NCoef="0" IVar="4" Cut="4.7300000000000000e+02" cType="1" res="0.0000000000000000e+00" rms="0.0000000000000000e+00" purity="0.0000000000000000e+00" nType="0">
          <Node pos="l" depth="2" NCoef="0" IVar="8" Cut="3.0000000000000000e+00" cType="1" res="6.2930425629019737e-03" rms="8.0110259354114532e-02" purity="0.0000000000000000e+00" nType="0">
            <Node pos="l" depth="3" NCoef="0" IVar="0" Cut="2.0000000000000000e+00" cType="1" res="-6.4040590077638626e-03" rms="6.8513020873069763e-02" purity="0.0000000000000000e+00" nType="0">
              <Node pos="l" depth="4" NCoef="0" IVar="8" Cut="1.0000000000000000e+00" cType="1" res="0.0000000000000000e+00" rms="0.0000000000000000e+00" purity="0.0000000000000000e+00" nType="0">
                <Node pos="l" depth="5" NCoef="0" IVar="-1" Cut="0.0000000000000000e+00" cType="1" res="4.6005607582628727e-03" rms="9.1734202578663826e-03" purity="0.0000000000000000e+00" nType="-99"/>
                <Node pos="r" depth="5" NCoef="0" IVar="-1" Cut="0.0000000000000000e+00" cType="1" res="-6.9317058660089970e-03" rms="5.6342218071222305e-02" purity="0.0000000000000000e+00" nType="-99"/>
              </Node>
              <Node pos="r" depth="4" NCoef="0" IVar="8" Cut="2.0000000000000000e+00" cType="1" res="-1.4709836104884744e-03" rms="6.2713623046875000e-02" purity="0.0000000000000000e+00" nType="0">
                <Node pos="l" depth="5" NCoef="0" IVar="-1" Cut="0.0000000000000000e+00" cType="1" res="-9.7308907425031066e-04" rms="5.4193891584873199e-02" purity="0.0000000000000000e+00" nType="-99"/>
                <Node pos="r" depth="5" NCoef="0" IVar="-1" Cut="0.0000000000000000e+00" cType="1" res="1.6439163591712713e-03" rms="7.8163020312786102e-02" purity="0.0000000000000000e+00" nType="-99"/>
              </Node>
            </Node>
            <Node pos="r" depth="3" NCoef="0" IVar="7" Cut="3.0000000000000000e+00" cType="1" res="1.5730487182736397e-02" rms="8.6953230202198029e-02" purity="0.0000000000000000e+00" nType="0">
              <Node pos="l" depth="4" NCoef="0" IVar="0" Cut="3.0000000000000000e+00" cType="1" res="2.1910877898335457e-02" rms="8.5591584444046021e-02" purity="0.0000000000000000e+00" nType="0">
                <Node pos="l" depth="5" NCoef="0" IVar="-1" Cut="0.0000000000000000e+00" cType="1" res="2.7725303079932928e-03" rms="8.6545147001743317e-02" purity="0.0000000000000000e+00" nType="-99"/>
                <Node pos="r" depth="5" NCoef="0" IVar="-1" Cut="0.0000000000000000e+00" cType="1" res="-2.6115023065358400e-03" rms="5.8175615966320038e-02" purity="0.0000000000000000e+00" nType="-99"/>
              </Node>
              <Node pos="r" depth="4" NCoef="0" IVar="8" Cut="6.0000000000000000e+00" cType="1" res="-4.5179791748523712e-02" rms="7.6213777065277100e-02" purity="0.0000000000000000e+00" nType="0">
                <Node pos="l" depth="5" NCoef="0" IVar="-1" Cut="0.0000000000000000e+00" cType="1" res="-1.6153155593201518e-03" rms="4.5105747878551483e-02" purity="0.0000000000000000e+00" nType="-99"/>
                <Node pos="r" depth="5" NCoef="0" IVar="-1" Cut="0.0000000000000000e+00" cType="1" res="-2.2033132612705231e-02" rms="0.0000000000000000e+00" purity="0.0000000000000000e+00" nType="-99"/>
              </Node>
            </Node>
          </Node>
          <Node pos="r" depth="2" NCoef="0" IVar="3" Cut="8.0000000000000000e+00" cType="1" res="0.0000000000000000e+00" rms="0.0000000000000000e+00" purity="0.0000000000000000e+00" nType="0">
            <Node pos="l" depth="3" NCoef="0" IVar="7" Cut="3.0000000000000000e+00" cType="1" res="-1.1930928565561771e-02" rms="4.4606916606426239e-02" purity="0.0000000000000000e+00" nType="0">
              <Node pos="l" depth="4" NCoef="0" IVar="0" Cut="2.2000000000000000e+01" cType="1" res="-5.0889026373624802e-02" rms="3.4050002694129944e-02" purity="0.0000000000000000e+00" nType="0">
                <Node pos="l" depth="5" NCoef="0" IVar="-1" Cut="0.0000000000000000e+00" cType="1" res="-5.9057860635221004e-03" rms="1.6998253762722015e-02" purity="0.0000000000000000e+00" nType="-99"/>
                <Node pos="r" depth="5" NCoef="0" IVar="-1" Cut="0.0000000000000000e+00" cType="1" res="4.2943940497934818e-03" rms="3.9837282150983810e-02" purity="0.0000000000000000e+00" nType="-99"/>
              </Node>
              <Node pos="r" depth="4" NCoef="0" IVar="8" Cut="2.0000000000000000e+00" cType="1" res="-6.2476750463247299e-03" rms="5.7290993630886078e-02" purity="0.0000000000000000e+00" nType="0">
                <Node pos="l" depth="5" NCoef="0" IVar="-1" Cut="0.0000000000000000e+00" cType="1" res="-2.4693615268915892e-03" rms="5.3825214505195618e-02" purity="0.0000000000000000e+00" nType="-99"/>
                <Node pos="r" depth="5" NCoef="0" IVar="-1" Cut="0.0000000000000000e+00" cType="1" res="1.2550444807857275e-03" rms="5.5448405444622040e-02" purity="0.0000000000000000e+00" nType="-99"/>
              </Node>
            </Node>
            <Node pos="r" depth="3" NCoef="0" IVar="3" Cut="1.3000000000000000e+01" cType="1" res="0.0000000000000000e+00" rms="0.0000000000000000e+00" purity="0.0000000000000000e+00" nType="0">
              <Node pos="l" depth="4" NCoef="0" IVar="0" Cut="4.0000000000000000e+00" cType="1" res="8.1443712115287781e-03" rms="5.3414173424243927e-02" purity="0.0000000000000000e+00" nType="0">
                <Node pos="l" depth="5" NCoef="0" IVar="-1" Cut="0.0000000000000000e+00" cType="1" res="2.9911282472312450e-03" rms="6.3362807035446167e-02" purity="0.0000000000000000e+00" nType="-99"/>
                <Node pos="r" depth="5" NCoef="0" IVar="-1" Cut="0.0000000000000000e+00" cType="1" res="-4.0754387737251818e-04" rms="4.2255789041519165e-02" purity="0.0000000000000000e+00" nType="-99"/>
              </Node>
              <Node pos="r" depth="4" NCoef="0" IVar="3" Cut="1.4000000000000000e+01" cType="1" res="0.0000000000000000e+00" rms="0.0000000000000000e+00" purity="0.0000000000000000e+00" nType="0">
                <Node pos="l" depth="5" NCoef="0" IVar="-1" Cut="0.0000000000000000e+00" cType="1" res="-5.7912725023925304e-03" rms="2.7699738740921021e-02" purity="0.0000000000000000e+00" nType="-99"/>
                <Node pos="r" depth="5" NCoef="0" IVar="-1" Cut="0.0000000000000000e+00" cType="1" res="4.4467527914093807e-05" rms="6.7454881966114044e-02" purity="0.0000000000000000e+00" nType="-99"/>
              </Node>
            </Node>
          </Node>
        </Node>
      </Node>
    </BinaryTree>
